odoo10_addon_stock_picking_invoicing-10.0.1.0.0.99.dev6-py3.8-nspkg.pth
odoo/addons/stock_picking_invoicing/README.rst
odoo/addons/stock_picking_invoicing/__init__.py
odoo/addons/stock_picking_invoicing/__manifest__.py
odoo/addons/stock_picking_invoicing/i18n/fr.po
odoo/addons/stock_picking_invoicing/i18n/sl.po
odoo/addons/stock_picking_invoicing/i18n/stock_picking_invoicing.pot
odoo/addons/stock_picking_invoicing/models/__init__.py
odoo/addons/stock_picking_invoicing/models/account_invoice.py
odoo/addons/stock_picking_invoicing/models/account_invoice_line.py
odoo/addons/stock_picking_invoicing/models/stock_invoice_state_mixin.py
odoo/addons/stock_picking_invoicing/models/stock_move.py
odoo/addons/stock_picking_invoicing/models/stock_picking.py
odoo/addons/stock_picking_invoicing/readme/CONTRIBUTORS.rst
odoo/addons/stock_picking_invoicing/readme/DESCRIPTION.rst
odoo/addons/stock_picking_invoicing/readme/USAGE.rst
odoo/addons/stock_picking_invoicing/static/description/icon.png
odoo/addons/stock_picking_invoicing/static/description/index.html
odoo/addons/stock_picking_invoicing/tests/__init__.py
odoo/addons/stock_picking_invoicing/tests/test_picking_invoicing.py
odoo/addons/stock_picking_invoicing/views/stock_move.xml
odoo/addons/stock_picking_invoicing/views/stock_picking.xml
odoo/addons/stock_picking_invoicing/wizards/__init__.py
odoo/addons/stock_picking_invoicing/wizards/stock_invoice_onshipping.py
odoo/addons/stock_picking_invoicing/wizards/stock_invoice_onshipping_view.xml
odoo10_addon_stock_picking_invoicing-10.0.1.0.0.99.dev6.dist-info/METADATA
odoo10_addon_stock_picking_invoicing-10.0.1.0.0.99.dev6.dist-info/WHEEL
odoo10_addon_stock_picking_invoicing-10.0.1.0.0.99.dev6.dist-info/namespace_packages.txt
odoo10_addon_stock_picking_invoicing-10.0.1.0.0.99.dev6.dist-info/top_level.txt
odoo10_addon_stock_picking_invoicing-10.0.1.0.0.99.dev6.dist-info/RECORD
